simple_redirects/__init__.py
simple_redirects/admin.py
simple_redirects/apps.py
simple_redirects/middleware.py
simple_redirects/models.py
simple_redirects/migrations/0001_initial.py
simple_redirects/migrations/__init__.py
django_simple_redirects-2.2.0.dist-info/LICENSE
django_simple_redirects-2.2.0.dist-info/METADATA
django_simple_redirects-2.2.0.dist-info/WHEEL
django_simple_redirects-2.2.0.dist-info/top_level.txt
django_simple_redirects-2.2.0.dist-info/RECORD
