Metadata-Version: 2.1
Name: django_simple_redirects
Version: 2.2.0
Summary: django.contrib.redirects without django.contrib.sites
Home-page: https://github.com/feinheit/django-simple-redirects/
Author: Matthias Kestenholz
Author-email: mk@feinheit.ch
License: MIT
Classifier: Environment :: Web Environment
Classifier: Framework :: Django
Classifier: Intended Audience :: Developers
Classifier: License :: OSI Approved :: MIT License
Classifier: Operating System :: OS Independent
Classifier: Programming Language :: Python
Classifier: Programming Language :: Python :: 3
Classifier: Programming Language :: Python :: 3 :: Only
Classifier: Programming Language :: Python :: 3.9
Classifier: Programming Language :: Python :: 3.10
Classifier: Programming Language :: Python :: 3.11
Classifier: Programming Language :: Python :: 3.12
Classifier: Topic :: Internet :: WWW/HTTP
Classifier: Topic :: Internet :: WWW/HTTP :: Dynamic Content
Requires-Python: >=3.8
License-File: LICENSE
Requires-Dist: Django >=3.2
Provides-Extra: tests
Requires-Dist: coverage ; extra == 'tests'
